coeusfactory/ConnectorFactory.py
coeusfactory/__init__.py
coeusfactory/connectors/BaseConnector.py
coeusfactory/connectors/DynamoConnector.py
coeusfactory/connectors/MongoConnector.py
coeusfactory/connectors/__init__.py
coeusfactory/repositories/BaseRepository.py
coeusfactory/repositories/DynamoRepository.py
coeusfactory/repositories/MongoRepository.py
coeusfactory/repositories/__init__.py
coeusfactory-0.7.0.dist-info/LICENSE
coeusfactory-0.7.0.dist-info/WHEEL
coeusfactory-0.7.0.dist-info/METADATA
coeusfactory-0.7.0.dist-info/RECORD
