Metadata-Version: 2.1
Name: coeusfactory
Version: 0.7.0
Summary: A Database Connector interface that follows a factory model pattern.
Home-page: https://github.com/mamerisawesome/coeusfactory
License: MIT
Keywords: database,database-factory,db-connector
Author: Almer Mendoza
Author-email: atmalmer23@gmail.com
Requires-Python: >=3.6,<4.0
Classifier: License :: OSI Approved :: MIT License
Classifier: Programming Language :: Python :: 3
Classifier: Programming Language :: Python :: 3.6
Classifier: Programming Language :: Python :: 3.7
Classifier: Programming Language :: Python :: 3.8
Requires-Dist: pypubsub (>=4.0.3,<5.0.0)
Project-URL: Repository, https://github.com/mamerisawesome/coeusfactory
